Workbook

Sheet Payment Summaries
C3: =IF(H9>Calcs!AQ9,"Jumbo 30 Yr Fix",IF(E15<0.2,"Conventional 30 Yr Fix - PMI Options","Conventional 30 Yr Fix")) -> Conventional 30 Yr Fix
C5: This sheet has been prepared for: | K5: Bollette
C7: Proposed Property Details | G7: =IF(E15<0.03,"",IF(E15<0.2,"Monthly PMI",IF(H9>Calcs!AQ9,"Jumbo 30 Yr Fix","Conventional 30 Yr Fix"))) -> Conventional 30 Yr Fix | J7: "No PMI"
C9: Purchase Price | E9: 750000 | G9: Loan Amount | H9: =E9*(1-E15) -> 600000 | J9: Loan Amount | K9: =H9 -> 600000
C10: Property Taxes (annual) | E10: 14000 | G10: Down Payment | H10: =$E$9*$E$15 -> 150000 | J10: Down Payment | K10: =H10 -> 150000
C11: Homowners Ins. (annual) | E11: 1800 | G11: Interest Rate | H11: 0.0625 | J11: Interest Rate | K11: =MROUND(Calcs!C8*100,1/8)/100 -> 0
C12: HOA fees | E12: 0 | G12: =IF($E$15<0.2,"PMI Rate","") | H12: =IF(E15<0.2,Calcs!C7,"")
C14: Client Details | G14: Monthly Payment | J14: Monthly Payment
C15: Down Payment | E15: 0.2 | G15: Principal & Interest | H15: =-PMT(H11/12,360,H9) -> 3694.3032 | J15: Principal & Interest | K15: =-PMT(K11/12,360,K9) -> 1666.6667
C16: Fico Score | E16: 771 | G16: Property Taxes | H16: =E10/12 -> 1166.6667 | J16: Property Taxes | K16: =E10/12 -> 1166.6667
C17: # of Borrowers | E17: Multi | G17: Homeowners Ins. | H17: =E11/12 -> 150 | J17: Homeowners Ins. | K17: =E11/12 -> 150
C18: First Time HomeBuyer | E18: Yes | G18: HOA/Maint | H18: =E12 -> 0 | J18: HOA/Maint | K18: =E12 -> 0
C19: HomePossible/HomeReady | E19: No | G19: =IF($E$15<0.2,"PMI","") | H19: =IF(E15<0.2,H9*H12/12,"")
C20: Your Monthly Budget | E20: 5000
C21: Your Max Allowable Payment | E21: 6324 | G21: Total Expense | H21: =SUM(H15:H19) -> 5010.9699 | J21: Total Expense | K21: =SUM(K15:K18) -> 2983.3333
G22: Total Cash to Close | H22: ='Payment Summaries'!E32 -> 168332.83 | J22: Total Cash to Close | K22: =E32-'Closing Cost Estimate'!G31+Calcs!AM10 -> 166770.33
C24: Cash to Close w/ monthly PMI | G24: Single Premium PMI - Paid in Full | J24: Single Premium PMI - Financed
C26: Purchase Price | E26: =E9 -> 750000 | G26: Loan Amount | H26: =H9 -> 600000 | J26: Loan Amount | K26: =H9+K30 -> 600000
C27: Down Paypayment | E27: =H10 -> 150000 | G27: Down Payment | H27: =H10 -> 150000 | J27: Down Payment | K27: =H10 -> 150000
C28: Closing Costs | E28: =SUM('Closing Cost Estimate'!G21,'Closing Cost Estimate'!G26,'Closing Cost Estimate'!M10,'Closing Cost Estimate'!M13,'Closing Cost Estimate'!M18) -> 8537 | G28: Interest Rate | H28: =H11 -> 0.0625 | J28: Interest Rate | K28: =H11 -> 0.0625
C29: Prepaid Items/Escrows | E29: =SUM('Closing Cost Estimate'!G29,'Closing Cost Estimate'!G33) -> 9795.8333 | G29: PMI Rate | H29: =Calcs!C9 -> 0 | J29: PMI Rate | K29: =Calcs!C10 -> 0
C30: Concessions/Credits | E30: 0 | G30: PMI Payment | H30: =H26*H29 -> 0 | J30: PMI Payment | K30: =(E9*0.9)*K29 -> 0
C32: Total Cash to Close | E32: =E27+E28+E29-E30 -> 168332.83 | G32: Monthly Payment | J32: Monthly Payment
G33: Principal & Interest | H33: =-PMT(H28/12,360,H26) -> 3694.3032 | J33: Principal & Interest | K33: =-PMT(K28/12,360,K26) -> 3694.3032
C34: Key: | G34: Property Taxes | H34: =E10/12 -> 1166.6667 | J34: Property Taxes | K34: =E10/12 -> 1166.6667
C35: Input fields | G35: Homeowners Ins. | H35: =E11/12 -> 150 | J35: Homeowners Ins. | K35: =E11/12 -> 150
C36: Locked fields | G36: HOA/Maint | H36: =E12 -> 0 | J36: HOA/Maint | K36: =E12 -> 0
C37: Payment Under Budget
C38: Over Budget, Can Qualify | G38: Total Expense | H38: =SUM(H33:H36) -> 5010.9699 | J38: Total Expense | K38: =SUM(K33:K36) -> 5010.9699
C39: Cannot Qualify | G39: Total Cash to Close | H39: =E32+H30 -> 168332.83 | J39: Total Cash to Close | K39: =E32-'Closing Cost Estimate'!G31+Calcs!AM11 -> 168332.83
C41: Dominick Russo | G41: Notes to Client:
C42: Cell: (201) 317-7900
C43: Loan Consultant
C44: NMLS #858889
C45: dom.russo@Luminate.Bank

Sheet Closing Cost Estimate
C3: Closing Cost Estimate
C5: This sheet has been prepared for: | M5: ='Payment Summaries'!K5 -> Bollette
C7: Your actual rate, payment, and costs could be higher. Get an official Loan Estimate before choosing a loan.
C9: Proposed Loan Terms | I9: Loan Costs
C10: Loan Purpose | G10: Purchase | I10: Origination Charges: | L10: Total: | M10: =SUM(M11:M12) -> 1595
C11: Occupancy | G11: Primary | I11: Commitment Fee | M11: 1595
C12: Loan/Amortization/Term | G12: 30 year Fixed | I12: Discount Points | L12: 0 | M12: =L12*F15 -> 0
I13: Services You Cannot Shop For: | L13: Total: | M13: =SUM(M14:M17) -> 794
C14: Purchase Price | F14: ='Payment Summaries'!E9 -> 750000 | I14: Appraisal Fee | M14: 475
C15: Loan Amount | F15: =F14*G18 -> 600000 | I15: Credit Report Fee | M15: 309
C16: Interest Rate | G16: ='Payment Summaries'!H11 -> 0.0625 | I16: Flood Certification | M16: 10
C17: APR | G17: =Calcs!AK17 -> 0.062886544 | I17: Tax Service Fee | M17: 0
C18: Loan to Value | G18: =1-'Payment Summaries'!E15 -> 0.8 | I18: Services You Can Shop For: | L18: Total: | M18: =SUM(M19:M29) -> 3980.25
I19: Title - Closing Protection Letter | M19: 75
C20: Other Costs and Prepaid Items | I20: Title - Settlement Fee | M20: 650
C21: Taxes and Govt. Fees: | E21: Total: | G21: =SUM(G22:G25) -> 436 | I21: Title - Courier Fee | M21: 60
C22: Govt. Recording Fee - Deed | G22: 83 | I22: Title - E Doc Title Fee | M22: 50
C23: Govt. Recording Fee - Mortgage | G23: 333 | I23: Title - Lender Title Insurance | M23: =Calcs!AN6 -> 2706.25
C24: Govt. Recording Fees | G24: 20 | I24: Title - Notary Fees | M24: 25
C25: NJ Mansion Tax | G25: =IF(F14>=1000000,F14*0.01,0) -> 0 | I25: Title - Recording Service Fee | M25: 15
C26: Other Fees: | E26: Total: | G26: =SUM(G27:G28) -> 1731.75 | I26: Title - Title Endorsement | M26: 100
C27: Borrower Attorney Fee | G27: 1500 | I27: Title - Title Examination | M27: 100
C28: Title - Owners Title Insurance | G28: =Calcs!AO6 -> 231.75 | I28: Title - Title Search | M28: 187
C29: Prepaid Items: | E29: Total: | G29: =SUM(G30:G32) -> 5695.8333 | I29: Title - Wire Transfer Fee | M29: 12
C30: Homeowners Insurance Premium | G30: ='Payment Summaries'!E11 -> 1800 | I30: Total Loan Costs: | M30: =SUM(M10,M13,M18) -> 6369.25
C31: PrePaid Interest - 15 days at | E31: ='Payment Summaries'!H9*G16/360 -> 104.16667 | G31: =E31*15 -> 1562.5
C32: Property Taxes - 2 months at | E32: ='Payment Summaries'!E10/12 -> 1166.6667 | G32: =E32*2 -> 2333.3333 | I32: Calculating Cash to Close
C33: Initial Escrow Collection: | E33: Total: | G33: =SUM(G34:G35) -> 4100 | I33: Total Closing Costs | M33: =SUM(G36,M30) -> 18332.833
C34: Homeowners Ins - 4 months at | E34: ='Payment Summaries'!E11/12 -> 150 | G34: =E34*4 -> 600 | I34: Down Payment | M34: =F14-F15 -> 150000
C35: Property Taxes - 3 months at | E35: ='Payment Summaries'!E10/12 -> 1166.6667 | G35: =E35*3 -> 3500 | I35: Seller's Concessions/Credits | M35: ='Payment Summaries'!E30 -> 0
C36: Total Other Costs and Prepaid Items: | G36: =SUM(G21,G26,G29,G33) -> 11963.583 | I36: Estimated Cash to Close | M36: =SUM(M33:M34)-M35 -> 168332.83
G38: Dominick Russo
G39: Loan Consultant
G40: NMLS # 858889
G41: Cell: (201) 317-7900
G42: dom.russo@Luminate.Bank

Sheet Amortization Schedule
C3: Amortization Schedule
C5: This sheet has been prepared for: | L5: ='Payment Summaries'!K5 -> Bollette
F7: Month | G7: Payment | H7: Principal | I7: Interest | J7: PMI | K7: Balance | L7: PrePayment
C9: Mort. Rate | D9: ='Payment Summaries'!H11 -> 0.0625 | F9: 1 | G9: =IF(D11=0,0,-PMT(D9/12,D12,D11)) -> 3694.3032 | H9: =G9-I9 -> 569.3032 | I9: =D11*D9/12 -> 3125 | J9: =IF(D11>=(D10*D14),D13,0) | K9: =IF(D11-H9-L9>0,D11-H9-L9,0) -> 599430.7 | L9: 0
C10: Purchase Price | D10: ='Payment Summaries'!E9 -> 750000 | F10: 2 | G10: =IF(K9=0,0,G9) -> 3694.3032 | H10: =G10-I10 -> 572.26832 | I10: =K9*D9/12 -> 3122.0349 | J10: =IF(K9>=(D10*D14),D13,0) -> 0 | K10: =IF(K9-H10-L10>0,K9-H10-L10,) -> 598858.43 | L10: 0
C11: Present Value | D11: ='Payment Summaries'!H9 -> 600000 | F11: 3 | G11: =IF(K10=0,0,G10) -> 3694.3032 | H11: =G11-I11 -> 575.24889 | I11: =K10*D9/12 -> 3119.0543 | J11: =IF(K10>=(D10*D14),D13,0) -> 0 | K11: =IF(K10-H11-L11>0,K10-H11-L11,) -> 598283.18 | L11: 0
C12: Length | D12: 360 | F12: 4 | G12: =IF(K11=0,0,G11) -> 3694.3032 | H12: =G12-I12 -> 578.24498 | I12: =K11*D9/12 -> 3116.0582 | J12: =IF(K11>=(D10*D14),D13,0) -> 0 | K12: =IF(K11-H12-L12>0,K11-H12-L12,) -> 597704.93 | L12: 0
C13: PMI Payment | D13: ='Payment Summaries'!H19 | F13: 5 | G13: =IF(K12=0,0,G12) -> 3694.3032 | H13: =G13-I13 -> 581.25667 | I13: =K12*D9/12 -> 3113.0465 | J13: =IF(K12>=(D10*D14),D13,0) -> 0 | K13: =IF(K12-H13-L13>0,K12-H13-L13,) -> 597123.68 | L13: 0
C14: PMI End | D14: 0.8 | F14: 6 | G14: =IF(K13=0,0,G13) -> 3694.3032 | H14: =G14-I14 -> 584.28405 | I14: =K13*D9/12 -> 3110.0192 | J14: =IF(K13>=(D10*D14),D13,0) -> 0 | K14: =IF(K13-H14-L14>0,K13-H14-L14,) -> 596539.39 | L14: 0
F15: 7 | G15: =IF(K14=0,0,G14) -> 3694.3032 | H15: =G15-I15 -> 587.32719 | I15: =K14*D9/12 -> 3106.976 | J15: =IF(K14>=(D10*D14),D13,0) -> 0 | K15: =IF(K14-H15-L15>0,K14-H15-L15,) -> 595952.07 | L15: 0
F16: 8 | G16: =IF(K15=0,0,G15) -> 3694.3032 | H16: =G16-I16 -> 590.38619 | I16: =K15*D9/12 -> 3103.917 | J16: =IF(K15>=(D10*D14),D13,0) -> 0 | K16: =IF(K15-H16-L16>0,K15-H16-L16,) -> 595361.68 | L16: 0
F17: 9 | G17: =IF(K16=0,0,G16) -> 3694.3032 | H17: =G17-I17 -> 593.46112 | I17: =K16*D9/12 -> 3100.8421 | J17: =IF(K16>=(D10*D14),D13,0) -> 0 | K17: =IF(K16-H17-L17>0,K16-H17-L17,) -> 594768.22 | L17: 0
F18: 10 | G18: =IF(K17=0,0,G17) -> 3694.3032 | H18: =G18-I18 -> 596.55206 | I18: =K17*D9/12 -> 3097.7511 | J18: =IF(K17>=(D10*D14),D13,0) -> 0 | K18: =IF(K17-H18-L18>0,K17-H18-L18,) -> 594171.67 | L18: 0
F19: 11 | G19: =IF(K18=0,0,G18) -> 3694.3032 | H19: =G19-I19 -> 599.6591 | I19: =K18*D9/12 -> 3094.6441 | J19: =IF(K18>=(D10*D14),D13,0) -> 0 | K19: =IF(K18-H19-L19>0,K18-H19-L19,) -> 593572.01 | L19: 0
F20: 12 | G20: =IF(K19=0,0,G19) -> 3694.3032 | H20: =G20-I20 -> 602.78233 | I20: =K19*D9/12 -> 3091.5209 | J20: =IF(K19>=(D10*D14),D13,0) -> 0 | K20: =IF(K19-H20-L20>0,K19-H20-L20,) -> 592969.23 | L20: 0
F21: 13 | G21: =IF(K20=0,0,G20) -> 3694.3032 | H21: =G21-I21 -> 605.92182 | I21: =K20*D9/12 -> 3088.3814 | J21: =IF(K20>=(D10*D14),D13,0) -> 0 | K21: =IF(K20-H21-L21>0,K20-H21-L21,) -> 592363.3 | L21: 0
F22: 14 | G22: =IF(K21=0,0,G21) -> 3694.3032 | H22: =G22-I22 -> 609.07766 | I22: =K21*D9/12 -> 3085.2255 | J22: =IF(K21>=(D10*D14),D13,0) -> 0 | K22: =IF(K21-H22-L22>0,K21-H22-L22,) -> 591754.23 | L22: 0
F23: 15 | G23: =IF(K22=0,0,G22) -> 3694.3032 | H23: =G23-I23 -> 612.24994 | I23: =K22*D9/12 -> 3082.0533 | J23: =IF(K22>=(D10*D14),D13,0) -> 0 | K23: =IF(K22-H23-L23>0,K22-H23-L23,) -> 591141.98 | L23: 0
F24: 16 | G24: =IF(K23=0,0,G23) -> 3694.3032 | H24: =G24-I24 -> 615.43874 | I24: =K23*D9/12 -> 3078.8645 | J24: =IF(K23>=(D10*D14),D13,0) -> 0 | K24: =IF(K23-H24-L24>0,K23-H24-L24,) -> 590526.54 | L24: 0
F25: 17 | G25: =IF(K24=0,0,G24) -> 3694.3032 | H25: =G25-I25 -> 618.64415 | I25: =K24*D9/12 -> 3075.6591 | J25: =IF(K24>=(D10*D14),D13,0) -> 0 | K25: =IF(K24-H25-L25>0,K24-H25-L25,) -> 589907.89 | L25: 0
F26: 18 | G26: =IF(K25=0,0,G25) -> 3694.3032 | H26: =G26-I26 -> 621.86626 | I26: =K25*D9/12 -> 3072.4369 | J26: =IF(K25>=(D10*D14),D13,0) -> 0 | K26: =IF(K25-H26-L26>0,K25-H26-L26,) -> 589286.03 | L26: 0
F27: 19 | G27: =IF(K26=0,0,G26) -> 3694.3032 | H27: =G27-I27 -> 625.10514 | I27: =K26*D9/12 -> 3069.1981 | J27: =IF(K26>=(D10*D14),D13,0) -> 0 | K27: =IF(K26-H27-L27>0,K26-H27-L27,) -> 588660.92 | L27: 0
F28: 20 | G28: =IF(K27=0,0,G27) -> 3694.3032 | H28: =G28-I28 -> 628.3609 | I28: =K27*D9/12 -> 3065.9423 | J28: =IF(K27>=(D10*D14),D13,0) -> 0 | K28: =IF(K27-H28-L28>0,K27-H28-L28,) -> 588032.56 | L28: 0
F29: 21 | G29: =IF(K28=0,0,G28) -> 3694.3032 | H29: =G29-I29 -> 631.63361 | I29: =K28*D9/12 -> 3062.6696 | J29: =IF(K28>=(D10*D14),D13,0) -> 0 | K29: =IF(K28-H29-L29>0,K28-H29-L29,) -> 587400.93 | L29: 0
F30: 22 | G30: =IF(K29=0,0,G29) -> 3694.3032 | H30: =G30-I30 -> 634.92337 | I30: =K29*D9/12 -> 3059.3798 | J30: =IF(K29>=(D10*D14),D13,0) -> 0 | K30: =IF(K29-H30-L30>0,K29-H30-L30,) -> 586766 | L30: 0
F31: 23 | G31: =IF(K30=0,0,G30) -> 3694.3032 | H31: =G31-I31 -> 638.23026 | I31: =K30*D9/12 -> 3056.0729 | J31: =IF(K30>=(D10*D14),D13,0) -> 0 | K31: =IF(K30-H31-L31>0,K30-H31-L31,) -> 586127.77 | L31: 0
F32: 24 | G32: =IF(K31=0,0,G31) -> 3694.3032 | H32: =G32-I32 -> 641.55438 | I32: =K31*D9/12 -> 3052.7488 | J32: =IF(K31>=(D10*D14),D13,0) -> 0 | K32: =IF(K31-H32-L32>0,K31-H32-L32,) -> 585486.22 | L32: 0
F33: 25 | G33: =IF(K32=0,0,G32) -> 3694.3032 | H33: =G33-I33 -> 644.89581 | I33: =K32*D9/12 -> 3049.4074 | J33: =IF(K32>=(D10*D14),D13,0) -> 0 | K33: =IF(K32-H33-L33>0,K32-H33-L33,) -> 584841.32 | L33: 0
F34: 26 | G34: =IF(K33=0,0,G33) -> 3694.3032 | H34: =G34-I34 -> 648.25464 | I34: =K33*D9/12 -> 3046.0486 | J34: =IF(K33>=(D10*D14),D13,0) -> 0 | K34: =IF(K33-H34-L34>0,K33-H34-L34,) -> 584193.07 | L34: 0
F35: 27 | G35: =IF(K34=0,0,G34) -> 3694.3032 | H35: =G35-I35 -> 651.63097 | I35: =K34*D9/12 -> 3042.6722 | J35: =IF(K34>=(D10*D14),D13,0) -> 0 | K35: =IF(K34-H35-L35>0,K34-H35-L35,) -> 583541.44 | L35: 0
F36: 28 | G36: =IF(K35=0,0,G35) -> 3694.3032 | H36: =G36-I36 -> 655.02488 | I36: =K35*D9/12 -> 3039.2783 | J36: =IF(K35>=(D10*D14),D13,0) -> 0 | K36: =IF(K35-H36-L36>0,K35-H36-L36,) -> 582886.41 | L36: 0
F37: 29 | G37: =IF(K36=0,0,G36) -> 3694.3032 | H37: =G37-I37 -> 658.43647 | I37: =K36*D9/12 -> 3035.8667 | J37: =IF(K36>=(D10*D14),D13,0) -> 0 | K37: =IF(K36-H37-L37>0,K36-H37-L37,) -> 582227.98 | L37: 0
F38: 30 | G38: =IF(K37=0,0,G37) -> 3694.3032 | H38: =G38-I38 -> 661.86582 | I38: =K37*D9/12 -> 3032.4374 | J38: =IF(K37>=(D10*D14),D13,0) -> 0 | K38: =IF(K37-H38-L38>0,K37-H38-L38,) -> 581566.11 | L38: 0
F39: 31 | G39: =IF(K38=0,0,G38) -> 3694.3032 | H39: =G39-I39 -> 665.31304 | I39: =K38*D9/12 -> 3028.9902 | J39: =IF(K38>=(D10*D14),D13,0) -> 0 | K39: =IF(K38-H39-L39>0,K38-H39-L39,) -> 580900.8 | L39: 0
F40: 32 | G40: =IF(K39=0,0,G39) -> 3694.3032 | H40: =G40-I40 -> 668.77821 | I40: =K39*D9/12 -> 3025.525 | J40: =IF(K39>=(D10*D14),D13,0) -> 0 | K40: =IF(K39-H40-L40>0,K39-H40-L40,) -> 580232.02 | L40: 0
F41: 33 | G41: =IF(K40=0,0,G40) -> 3694.3032 | H41: =G41-I41 -> 672.26143 | I41: =K40*D9/12 -> 3022.0418 | J41: =IF(K40>=(D10*D14),D13,0) -> 0 | K41: =IF(K40-H41-L41>0,K40-H41-L41,) -> 579559.76 | L41: 0
F42: 34 | G42: =IF(K41=0,0,G41) -> 3694.3032 | H42: =G42-I42 -> 675.76279 | I42: =K41*D9/12 -> 3018.5404 | J42: =IF(K41>=(D10*D14),D13,0) -> 0 | K42: =IF(K41-H42-L42>0,K41-H42-L42,) -> 578884 | L42: 0
F43: 35 | G43: =IF(K42=0,0,G42) -> 3694.3032 | H43: =G43-I43 -> 679.28239 | I43: =K42*D9/12 -> 3015.0208 | J43: =IF(K42>=(D10*D14),D13,0) -> 0 | K43: =IF(K42-H43-L43>0,K42-H43-L43,) -> 578204.71 | L43: 0
F44: 36 | G44: =IF(K43=0,0,G43) -> 3694.3032 | H44: =G44-I44 -> 682.82032 | I44: =K43*D9/12 -> 3011.4829 | J44: =IF(K43>=(D10*D14),D13,0) -> 0 | K44: =IF(K43-H44-L44>0,K43-H44-L44,) -> 577521.89 | L44: 0
F48: Month | G48: Payment | H48: Principal | I48: Interest | J48: PMI | K48: Balance | L48: PrePayment
C50: Rate | D50: =D9 -> 0.0625 | F50: 37 | G50: =IF(K44=0,0,G44) -> 3694.3032 | H50: =G50-I50 -> 686.37668 | I50: =K44*D50/12 -> 3007.9265 | J50: =IF(K44>=(D51*D55),D54,0) -> 0 | K50: =IF(K44-H50-L50>0,K44-H50-L50,0) -> 576835.52 | L50: 0
C51: Purchase Price | D51: =D10 -> 750000 | F51: 38 | G51: =IF(K50=0,0,G50) -> 3694.3032 | H51: =G51-I51 -> 689.95156 | I51: =K50*D50/12 -> 3004.3516 | J51: =IF(K50>=(D51*D55),D54,0) -> 0 | K51: =IF(K50-H51-L51>0,K50-H51-L51,) -> 576145.56 | L51: 0
C52: Present Value | D52: =D11 -> 600000 | F52: 39 | G52: =IF(K51=0,0,G51) -> 3694.3032 | H52: =G52-I52 -> 693.54505 | I52: =K51*D50/12 -> 3000.7581 | J52: =IF(K51>=(D51*D55),D54,0) -> 0 | K52: =IF(K51-H52-L52>0,K51-H52-L52,) -> 575452.02 | L52: 0
C53: Length | D53: =D12 -> 360 | F53: 40 | G53: =IF(K52=0,0,G52) -> 3694.3032 | H53: =G53-I53 -> 697.15727 | I53: =K52*D50/12 -> 2997.1459 | J53: =IF(K52>=(D51*D55),D54,0) -> 0 | K53: =IF(K52-H53-L53>0,K52-H53-L53,) -> 574754.86 | L53: 0
C54: PMI Payment | D54: =D13 | F54: 41 | G54: =IF(K53=0,0,G53) -> 3694.3032 | H54: =G54-I54 -> 700.78829 | I54: =K53*D50/12 -> 2993.5149 | J54: =IF(K53>=(D51*D55),D54,0) -> 0 | K54: =IF(K53-H54-L54>0,K53-H54-L54,) -> 574054.07 | L54: 0
C55: PMI End | D55: =D14 -> 0.8 | F55: 42 | G55: =IF(K54=0,0,G54) -> 3694.3032 | H55: =G55-I55 -> 704.43823 | I55: =K54*D50/12 -> 2989.865 | J55: =IF(K54>=(D51*D55),D54,0) -> 0 | K55: =IF(K54-H55-L55>0,K54-H55-L55,) -> 573349.64 | L55: 0
F56: 43 | G56: =IF(K55=0,0,G55) -> 3694.3032 | H56: =G56-I56 -> 708.10718 | I56: =K55*D50/12 -> 2986.196 | J56: =IF(K55>=(D51*D55),D54,0) -> 0 | K56: =IF(K55-H56-L56>0,K55-H56-L56,) -> 572641.53 | L56: 0
F57: 44 | G57: =IF(K56=0,0,G56) -> 3694.3032 | H57: =G57-I57 -> 711.79524 | I57: =K56*D50/12 -> 2982.508 | J57: =IF(K56>=(D51*D55),D54,0) -> 0 | K57: =IF(K56-H57-L57>0,K56-H57-L57,) -> 571929.73 | L57: 0
F58: 45 | G58: =IF(K57=0,0,G57) -> 3694.3032 | H58: =G58-I58 -> 715.50251 | I58: =K57*D50/12 -> 2978.8007 | J58: =IF(K57>=(D51*D55),D54,0) -> 0 | K58: =IF(K57-H58-L58>0,K57-H58-L58,) -> 571214.23 | L58: 0
F59: 46 | G59: =IF(K58=0,0,G58) -> 3694.3032 | H59: =G59-I59 -> 719.22908 | I59: =K58*D50/12 -> 2975.0741 | J59: =IF(K58>=(D51*D55),D54,0) -> 0 | K59: =IF(K58-H59-L59>0,K58-H59-L59,) -> 570495 | L59: 0
F60: 47 | G60: =IF(K59=0,0,G59) -> 3694.3032 | H60: =G60-I60 -> 722.97507 | I60: =K59*D50/12 -> 2971.3281 | J60: =IF(K59>=(D51*D55),D54,0) -> 0 | K60: =IF(K59-H60-L60>0,K59-H60-L60,) -> 569772.03 | L60: 0
F61: 48 | G61: =IF(K60=0,0,G60) -> 3694.3032 | H61: =G61-I61 -> 726.74056 | I61: =K60*D50/12 -> 2967.5626 | J61: =IF(K60>=(D51*D55),D54,0) -> 0 | K61: =IF(K60-H61-L61>0,K60-H61-L61,) -> 569045.29 | L61: 0
F62: 49 | G62: =IF(K61=0,0,G61) -> 3694.3032 | H62: =G62-I62 -> 730.52567 | I62: =K61*D50/12 -> 2963.7775 | J62: =IF(K61>=(D51*D55),D54,0) -> 0 | K62: =IF(K61-H62-L62>0,K61-H62-L62,) -> 568314.76 | L62: 0
F63: 50 | G63: =IF(K62=0,0,G62) -> 3694.3032 | H63: =G63-I63 -> 734.33049 | I63: =K62*D50/12 -> 2959.9727 | J63: =IF(K62>=(D51*D55),D54,0) -> 0 | K63: =IF(K62-H63-L63>0,K62-H63-L63,) -> 567580.43 | L63: 0
F64: 51 | G64: =IF(K63=0,0,G63) -> 3694.3032 | H64: =G64-I64 -> 738.15513 | I64: =K63*D50/12 -> 2956.1481 | J64: =IF(K63>=(D51*D55),D54,0) -> 0 | K64: =IF(K63-H64-L64>0,K63-H64-L64,) -> 566842.27 | L64: 0
F65: 52 | G65: =IF(K64=0,0,G64) -> 3694.3032 | H65: =G65-I65 -> 741.99969 | I65: =K64*D50/12 -> 2952.3035 | J65: =IF(K64>=(D51*D55),D54,0) -> 0 | K65: =IF(K64-H65-L65>0,K64-H65-L65,) -> 566100.28 | L65: 0
F66: 53 | G66: =IF(K65=0,0,G65) -> 3694.3032 | H66: =G66-I66 -> 745.86427 | I66: =K65*D50/12 -> 2948.4389 | J66: =IF(K65>=(D51*D55),D54,0) -> 0 | K66: =IF(K65-H66-L66>0,K65-H66-L66,) -> 565354.41 | L66: 0
F67: 54 | G67: =IF(K66=0,0,G66) -> 3694.3032 | H67: =G67-I67 -> 749.74898 | I67: =K66*D50/12 -> 2944.5542 | J67: =IF(K66>=(D51*D55),D54,0) -> 0 | K67: =IF(K66-H67-L67>0,K66-H67-L67,) -> 564604.66 | L67: 0
F68: 55 | G68: =IF(K67=0,0,G67) -> 3694.3032 | H68: =G68-I68 -> 753.65392 | I68: =K67*D50/12 -> 2940.6493 | J68: =IF(K67>=(D51*D55),D54,0) -> 0 | K68: =IF(K67-H68-L68>0,K67-H68-L68,) -> 563851.01 | L68: 0
F69: 56 | G69: =IF(K68=0,0,G68) -> 3694.3032 | H69: =G69-I69 -> 757.5792 | I69: =K68*D50/12 -> 2936.724 | J69: =IF(K68>=(D51*D55),D54,0) -> 0 | K69: =IF(K68-H69-L69>0,K68-H69-L69,) -> 563093.43 | L69: 0
F70: 57 | G70: =IF(K69=0,0,G69) -> 3694.3032 | H70: =G70-I70 -> 761.52493 | I70: =K69*D50/12 -> 2932.7783 | J70: =IF(K69>=(D51*D55),D54,0) -> 0 | K70: =IF(K69-H70-L70>0,K69-H70-L70,) -> 562331.9 | L70: 0
F71: 58 | G71: =IF(K70=0,0,G70) -> 3694.3032 | H71: =G71-I71 -> 765.4912 | I71: =K70*D50/12 -> 2928.812 | J71: =IF(K70>=(D51*D55),D54,0) -> 0 | K71: =IF(K70-H71-L71>0,K70-H71-L71,) -> 561566.41 | L71: 0
F72: 59 | G72: =IF(K71=0,0,G71) -> 3694.3032 | H72: =G72-I72 -> 769.47814 | I72: =K71*D50/12 -> 2924.8251 | J72: =IF(K71>=(D51*D55),D54,0) -> 0 | K72: =IF(K71-H72-L72>0,K71-H72-L72,) -> 560796.93 | L72: 0
F73: 60 | G73: =IF(K72=0,0,G72) -> 3694.3032 | H73: =G73-I73 -> 773.48584 | I73: =K72*D50/12 -> 2920.8174 | J73: =IF(K72>=(D51*D55),D54,0) -> 0 | K73: =IF(K72-H73-L73>0,K72-H73-L73,) -> 560023.45 | L73: 0
F74: 61 | G74: =IF(K73=0,0,G73) -> 3694.3032 | H74: =G74-I74 -> 777.51441 | I74: =K73*D50/12 -> 2916.7888 | J74: =IF(K73>=(D51*D55),D54,0) -> 0 | K74: =IF(K73-H74-L74>0,K73-H74-L74,) -> 559245.93 | L74: 0
F75: 62 | G75: =IF(K74=0,0,G74) -> 3694.3032 | H75: =G75-I75 -> 781.56396 | I75: =K74*D50/12 -> 2912.7392 | J75: =IF(K74>=(D51*D55),D54,0) -> 0 | K75: =IF(K74-H75-L75>0,K74-H75-L75,) -> 558464.37 | L75: 0
F76: 63 | G76: =IF(K75=0,0,G75) -> 3694.3032 | H76: =G76-I76 -> 785.63461 | I76: =K75*D50/12 -> 2908.6686 | J76: =IF(K75>=(D51*D55),D54,0) -> 0 | K76: =IF(K75-H76-L76>0,K75-H76-L76,) -> 557678.74 | L76: 0
F77: 64 | G77: =IF(K76=0,0,G76) -> 3694.3032 | H77: =G77-I77 -> 789.72645 | I77: =K76*D50/12 -> 2904.5767 | J77: =IF(K76>=(D51*D55),D54,0) -> 0 | K77: =IF(K76-H77-L77>0,K76-H77-L77,) -> 556889.01 | L77: 0
F78: 65 | G78: =IF(K77=0,0,G77) -> 3694.3032 | H78: =G78-I78 -> 793.83961 | I78: =K77*D50/12 -> 2900.4636 | J78: =IF(K77>=(D51*D55),D54,0) -> 0 | K78: =IF(K77-H78-L78>0,K77-H78-L78,) -> 556095.17 | L78: 0
F79: 66 | G79: =IF(K78=0,0,G78) -> 3694.3032 | H79: =G79-I79 -> 797.97419 | I79: =K78*D50/12 -> 2896.329 | J79: =IF(K78>=(D51*D55),D54,0) -> 0 | K79: =IF(K78-H79-L79>0,K78-H79-L79,) -> 555297.2 | L79: 0
F80: 67 | G80: =IF(K79=0,0,G79) -> 3694.3032 | H80: =G80-I80 -> 802.13031 | I80: =K79*D50/12 -> 2892.1729 | J80: =IF(K79>=(D51*D55),D54,0) -> 0 | K80: =IF(K79-H80-L80>0,K79-H80-L80,) -> 554495.07 | L80: 0
F81: 68 | G81: =IF(K80=0,0,G80) -> 3694.3032 | H81: =G81-I81 -> 806.30807 | I81: =K80*D50/12 -> 2887.9951 | J81: =IF(K80>=(D51*D55),D54,0) -> 0 | K81: =IF(K80-H81-L81>0,K80-H81-L81,) -> 553688.76 | L81: 0
F82: 69 | G82: =IF(K81=0,0,G81) -> 3694.3032 | H82: =G82-I82 -> 810.50759 | I82: =K81*D50/12 -> 2883.7956 | J82: =IF(K81>=(D51*D55),D54,0) -> 0 | K82: =IF(K81-H82-L82>0,K81-H82-L82,) -> 552878.25 | L82: 0
F83: 70 | G83: =IF(K82=0,0,G82) -> 3694.3032 | H83: =G83-I83 -> 814.72899 | I83: =K82*D50/12 -> 2879.5742 | J83: =IF(K82>=(D51*D55),D54,0) -> 0 | K83: =IF(K82-H83-L83>0,K82-H83-L83,) -> 552063.52 | L83: 0
F84: 71 | G84: =IF(K83=0,0,G83) -> 3694.3032 | H84: =G84-I84 -> 818.97237 | I84: =K83*D50/12 -> 2875.3308 | J84: =IF(K83>=(D51*D55),D54,0) -> 0 | K84: =IF(K83-H84-L84>0,K83-H84-L84,) -> 551244.55 | L84: 0
F85: 72 | G85: =IF(K84=0,0,G84) -> 3694.3032 | H85: =G85-I85 -> 823.23785 | I85: =K84*D50/12 -> 2871.0654 | J85: =IF(K84>=(D51*D55),D54,0) -> 0 | K85: =IF(K84-H85-L85>0,K84-H85-L85,) -> 550421.31 | L85: 0
C86: Rate | D86: =D50 -> 0.0625 | F86: 73 | G86: =IF(K85=0,0,G85) -> 3694.3032 | H86: =G86-I86 -> 827.52554 | I86: =K85*D86/12 -> 2866.7777 | J86: =IF(K85>=(D87*D91),D90,0) -> 0 | K86: =IF(K85-H86-L86>0,K85-H86-L86,) -> 549593.78 | L86: 0
C87: Purchase Price | D87: =D51 -> 750000 | F87: 74 | G87: =IF(K86=0,0,G86) -> 3694.3032 | H87: =G87-I87 -> 831.83557 | I87: =K86*D86/12 -> 2862.4676 | J87: =IF(K86>=(D87*D91),D90,0) -> 0 | K87: =IF(K86-H87-L87>0,K86-H87-L87,) -> 548761.95 | L87: 0
C88: Present Value | D88: =D52 -> 600000 | F88: 75 | G88: =IF(K87=0,0,G87) -> 3694.3032 | H88: =G88-I88 -> 836.16805 | I88: =K87*D86/12 -> 2858.1352 | J88: =IF(K87>=(D87*D91),D90,0) -> 0 | K88: =IF(K87-H88-L88>0,K87-H88-L88,) -> 547925.78 | L88: 0
C89: Length | D89: =D53 -> 360 | F89: 76 | G89: =IF(K88=0,0,G88) -> 3694.3032 | H89: =G89-I89 -> 840.52309 | I89: =K88*D86/12 -> 2853.7801 | J89: =IF(K88>=(D87*D91),D90,0) -> 0 | K89: =IF(K88-H89-L89>0,K88-H89-L89,) -> 547085.26 | L89: 0
C90: PMI Payment | D90: =D54 | F90: 77 | G90: =IF(K89=0,0,G89) -> 3694.3032 | H90: =G90-I90 -> 844.90082 | I90: =K89*D86/12 -> 2849.4024 | J90: =IF(K89>=(D87*D91),D90,0) -> 0 | K90: =IF(K89-H90-L90>0,K89-H90-L90,) -> 546240.36 | L90: 0
C91: PMI End | D91: =D55 -> 0.8 | F91: 78 | G91: =IF(K90=0,0,G90) -> 3694.3032 | H91: =G91-I91 -> 849.30134 | I91: =K90*D86/12 -> 2845.0019 | J91: =IF(K90>=(D87*D91),D90,0) -> 0 | K91: =IF(K90-H91-L91>0,K90-H91-L91,) -> 545391.06 | L91: 0
F95: Month | G95: Payment | H95: Principal | I95: Interest | J95: PMI | K95: Balance | L95: PrePayment
F97: 79 | G97: =IF(K91=0,0,G91) -> 3694.3032 | H97: =G97-I97 -> 853.72479 | I97: =K91*D86/12 -> 2840.5784 | J97: =IF(K91>=(D87*D91),D90,0) -> 0 | K97: =IF(K91-H97-L97>0,K91-H97-L97,0) -> 544537.33 | L97: 0
F98: 80 | G98: =IF(K97=0,0,G97) -> 3694.3032 | H98: =G98-I98 -> 858.17127 | I98: =K97*D86/12 -> 2836.1319 | J98: =IF(K97>=(D87*D91),D90,0) -> 0 | K98: =IF(K97-H98-L98>0,K97-H98-L98,) -> 543679.16 | L98: 0
F99: 81 | G99: =IF(K98=0,0,G98) -> 3694.3032 | H99: =G99-I99 -> 862.64091 | I99: =K98*D86/12 -> 2831.6623 | J99: =IF(K98>=(D87*D91),D90,0) -> 0 | K99: =IF(K98-H99-L99>0,K98-H99-L99,) -> 542816.52 | L99: 0
F100: 82 | G100: =IF(K99=0,0,G99) -> 3694.3032 | H100: =G100-I100 -> 867.13383 | I100: =K99*D86/12 -> 2827.1694 | J100: =IF(K99>=(D87*D91),D90,0) -> 0 | K100: =IF(K99-H100-L100>0,K99-H100-L100,) -> 541949.39 | L100: 0
F101: 83 | G101: =IF(K100=0,0,G100) -> 3694.3032 | H101: =G101-I101 -> 871.65016 | I101: =K100*D86/12 -> 2822.653 | J101: =IF(K100>=(D87*D91),D90,0) -> 0 | K101: =IF(K100-H101-L101>0,K100-H101-L101,) -> 541077.73 | L101: 0
F102: 84 | G102: =IF(K101=0,0,G101) -> 3694.3032 | H102: =G102-I102 -> 876.19 | I102: =K101*D86/12 -> 2818.1132 | J102: =IF(K101>=(D87*D91),D90,0) -> 0 | K102: =IF(K101-H102-L102>0,K101-H102-L102,) -> 540201.54 | L102: 0
F103: 85 | G103: =IF(K102=0,0,G102) -> 3694.3032 | H103: =G103-I103 -> 880.75349 | I103: =K102*D86/12 -> 2813.5497 | J103: =IF(K102>=(D87*D91),D90,0) -> 0 | K103: =IF(K102-H103-L103>0,K102-H103-L103,) -> 539320.79 | L103: 0
F104: 86 | G104: =IF(K103=0,0,G103) -> 3694.3032 | H104: =G104-I104 -> 885.34075 | I104: =K103*D86/12 -> 2808.9625 | J104: =IF(K103>=(D87*D91),D90,0) -> 0 | K104: =IF(K103-H104-L104>0,K103-H104-L104,) -> 538435.45 | L104: 0
F105: 87 | G105: =IF(K104=0,0,G104) -> 3694.3032 | H105: =G105-I105 -> 889.9519 | I105: =K104*D86/12 -> 2804.3513 | J105: =IF(K104>=(D87*D91),D90,0) -> 0 | K105: =IF(K104-H105-L105>0,K104-H105-L105,) -> 537545.5 | L105: 0
F106: 88 | G106: =IF(K105=0,0,G105) -> 3694.3032 | H106: =G106-I106 -> 894.58706 | I106: =K105*D86/12 -> 2799.7161 | J106: =IF(K105>=(D87*D91),D90,0) -> 0 | K106: =IF(K105-H106-L106>0,K105-H106-L106,) -> 536650.91 | L106: 0
F107: 89 | G107: =IF(K106=0,0,G106) -> 3694.3032 | H107: =G107-I107 -> 899.24637 | I107: =K106*D86/12 -> 2795.0568 | J107: =IF(K106>=(D87*D91),D90,0) -> 0 | K107: =IF(K106-H107-L107>0,K106-H107-L107,) -> 535751.67 | L107: 0
F108: 90 | G108: =IF(K107=0,0,G107) -> 3694.3032 | H108: =G108-I108 -> 903.92995 | I108: =K107*D86/12 -> 2790.3733 | J108: =IF(K107>=(D87*D91),D90,0) -> 0 | K108: =IF(K107-H108-L108>0,K107-H108-L108,) -> 534847.74 | L108: 0
F109: 91 | G109: =IF(K108=0,0,G108) -> 3694.3032 | H109: =G109-I109 -> 908.63791 | I109: =K108*D86/12 -> 2785.6653 | J109: =IF(K108>=(D87*D91),D90,0) -> 0 | K109: =IF(K108-H109-L109>0,K108-H109-L109,) -> 533939.1 | L109: 0
F110: 92 | G110: =IF(K109=0,0,G109) -> 3694.3032 | H110: =G110-I110 -> 913.3704 | I110: =K109*D86/12 -> 2780.9328 | J110: =IF(K109>=(D87*D91),D90,0) -> 0 | K110: =IF(K109-H110-L110>0,K109-H110-L110,) -> 533025.73 | L110: 0
F111: 93 | G111: =IF(K110=0,0,G110) -> 3694.3032 | H111: =G111-I111 -> 918.12754 | I111: =K110*D86/12 -> 2776.1757 | J111: =IF(K110>=(D87*D91),D90,0) -> 0 | K111: =IF(K110-H111-L111>0,K110-H111-L111,) -> 532107.6 | L111: 0
F112: 94 | G112: =IF(K111=0,0,G111) -> 3694.3032 | H112: =G112-I112 -> 922.90945 | I112: =K111*D86/12 -> 2771.3937 | J112: =IF(K111>=(D87*D91),D90,0) -> 0 | K112: =IF(K111-H112-L112>0,K111-H112-L112,) -> 531184.69 | L112: 0
F113: 95 | G113: =IF(K112=0,0,G112) -> 3694.3032 | H113: =G113-I113 -> 927.71627 | I113: =K112*D86/12 -> 2766.5869 | J113: =IF(K112>=(D87*D91),D90,0) -> 0 | K113: =IF(K112-H113-L113>0,K112-H113-L113,) -> 530256.97 | L113: 0
...

Sheet Calcs
I2: 30 Yr Term - Black Box PMI Rates
E4: LTV | F4: =1-'Payment Summaries'!$E$15 -> 0.8 | I4: 3% Down - PMI Premiums - 1 Borrower | P4: 10% Down - PMI Premiums - 1 Borrower | W4: 3% Down - PMI Premiums - Multi Borrower | AD4: 10% Down - PMI Premiums - Multi Borrower | AJ4: Title Insurance Calculations | AQ4: 1
E5: Fico Score | F5: ='Payment Summaries'!$E$16 -> 771 | I5: Fico Range | J5: BPMI | K5: LPMI | L5: Single PIF | M5: Single Fin | P5: Fico Range | Q5: BPMI | R5: LPMI | S5: Single PIF | T5: Single Fin | W5: Fico Range | X5: BPMI | Y5: LPMI | Z5: Single PIF | AA5: Single Fin | AD5: Fico Range | AE5: BPMI | AF5: LPMI | AG5: Single PIF | AH5: Single Fin | AJ5: PP Round Up | AK5: Total Premium | AL5: DP | AM5: LA Round Up | AN5: Lenders | AO5: Owners | AQ5: Multi
E6: # of Borr | F6: ='Payment Summaries'!$E$17 -> Multi | H6: =IF($F$5>=800,J15,IF($F$5>=780,J14,IF($F$5>=760,J13,IF($F$5>=740,J12,IF($F$5>=720,J11,IF($F$5>=700,J10,IF($F$5>=680,J9,IF($F$5>=660,J8,IF($F$5>=640,J7,IF($F$5>=620,J6,0)))))))))) -> 0.0045 | I6: 620-639 | J6: 0.0186 | L6: 0.0655 | M6: 0.0521 | O6: =IF($F$5>=800,Q15,IF($F$5>=780,Q14,IF($F$5>=760,Q13,IF($F$5>=740,Q12,IF($F$5>=720,Q11,IF($F$5>=700,Q10,IF($F$5>=680,Q9,IF($F$5>=660,Q8,IF($F$5>=640,Q7,IF($F$5>=620,Q6,0)))))))))) -> 0.002 | P6: 620-639 | Q6: 0.0085 | S6: 0.0384 | T6: 0.0281 | V6: =IF($F$5>=800,X15,IF($F$5>=780,X14,IF($F$5>=760,X13,IF($F$5>=740,X12,IF($F$5>=720,X11,IF($F$5>=700,X10,IF($F$5>=680,X9,IF($F$5>=660,X8,IF($F$5>=640,X7,IF($F$5>=620,X6,0)))))))))) -> 0.0038 | W6: 620-639 | X6: 0.0168 | Z6: 0.0628 | AA6: 0.0521 | AC6: =IF($F$5>=800,AE15,IF($F$5>=780,AE14,IF($F$5>=760,AE13,IF($F$5>=740,AE12,IF($F$5>=720,AE11,IF($F$5>=700,AE10,IF($F$5>=680,AE9,IF($F$5>=660,AE8,IF($F$5>=640,AE7,IF($F$5>=620,AE6,0)))))))))) -> 0.0018 | AD6: 620-639 | AE6: 0.007 | AG6: 0.0369 | AH6: 0.0281 | AJ6: =ROUNDUP('Payment Summaries'!E9,-3) -> 750000 | AK6: =ROUND(IF(AJ6<0,AJ6,IF(AJ6<100001,AJ6*0.525%,IF(AJ6>2000000,6350+(AJ6-2000000)*0.2%,IF(AJ6>500000,2225+(AJ6-500000)*0.275%,IF(AJ6>100000,525+(AJ6-100000)*0.425%,))))),0) -> 2913 | AL6: 0.1 | AM6: =ROUNDUP(AJ6*(1-AL6),-3) -> 675000 | AN6: =IF(AM6<0,AM6,IF(AM6<100001,AM6*0.525%,IF(AM6>2000000,6350+(AM6-2000000)*0.2%,IF(AM6>500000,2225+(AM6-500000)*0.275%,IF(AM6>100000,525+(AM6-100000)*0.425%,))))) -> 2706.25 | AO6: =AK6-AN6+25 -> 231.75
B7: BPMI | C7: =IF('Payment Summaries'!$E$19="No",F7,F35) -> 0 | E7: BPMI | F7: =IF($F$4>0.97,0,IF(AND($F$4>0.95,$F$6=1),H6,IF(AND($F$4>0.95,$F$6="Multi"),V6,IF(AND($F$4>0.9,$F$6=1),H19,IF(AND($F$4>0.9,$F$6="Multi"),V19,IF(AND($F$4>0.85,$F$6=1),O6,IF(AND($F$4>0.85,$F$6="Multi"),AC6,IF(AND($F$4>0.8,$F$6=1),O19,IF(AND($F$4>0.8,$F$6="Multi"),AC19,))))))))) -> 0 | H7: =IF($F$5>=800,K15,IF($F$5>=780,K14,IF($F$5>=760,K13,IF($F$5>=740,K12,IF($F$5>=720,K11,IF($F$5>=700,K10,IF($F$5>=680,K9,IF($F$5>=660,K8,IF($F$5>=640,K7,IF($F$5>=620,K6,0)))))))))) -> 0.00625 | I7: 640-659 | J7: 0.0165 | L7: 0.0598 | M7: 0.0493 | O7: =IF($F$5>=800,R15,IF($F$5>=780,R14,IF($F$5>=760,R13,IF($F$5>=740,R12,IF($F$5>=720,R11,IF($F$5>=700,R10,IF($F$5>=680,R9,IF($F$5>=660,R8,IF($F$5>=640,R7,IF($F$5>=620,R6,0)))))))))) -> 0.0035 | P7: 640-659 | Q7: 0.0085 | S7: 0.0351 | T7: 0.0265 | V7: =IF($F$5>=800,Y15,IF($F$5>=780,Y14,IF($F$5>=760,Y13,IF($F$5>=740,Y12,IF($F$5>=720,Y11,IF($F$5>=700,Y10,IF($F$5>=680,Y9,IF($F$5>=660,Y8,IF($F$5>=640,Y7,IF($F$5>=620,Y6,0)))))))))) -> 0.0055 | W7: 640-659 | X7: 0.0147 | Z7: 0.0575 | AA7: 0.047 | AC7: =IF($F$5>=800,AF15,IF($F$5>=780,AF14,IF($F$5>=760,AF13,IF($F$5>=740,AF12,IF($F$5>=720,AF11,IF($F$5>=700,AF10,IF($F$5>=680,AF9,IF($F$5>=660,AF8,IF($F$5>=640,AF7,IF($F$5>=620,AF6,0)))))))))) -> 0.003 | AD7: 640-659 | AE7: 0.0071 | AG7: 0.0339 | AH7: 0.0253
B8: LPMI | C8: =IF('Payment Summaries'!$E$19="No",F8,F36) -> 0 | E8: LPMI | F8: =IF($F$4>0.97,0,IF(AND($F$4>0.95,$F$6=1),F12+H7,IF(AND($F$4>0.95,$F$6="Multi"),F12+V7,IF(AND($F$4>0.9,$F$6=1),F12+H20,IF(AND($F$4>0.9,$F$6="Multi"),F12+V20,IF(AND($F$4>0.85,$F$6=1),F12+O7,IF(AND($F$4>0.85,$F$6="Multi"),F12+AC7,IF(AND($F$4>0.8,$F$6=1),F12+O20,IF(AND($F$4>0.8,$F$6="Multi"),F12+AC20,))))))))) -> 0 | H8: =IF($F$5>=800,L15,IF($F$5>=780,L14,IF($F$5>=760,L13,IF($F$5>=740,L12,IF($F$5>=720,L11,IF($F$5>=700,L10,IF($F$5>=680,L9,IF($F$5>=660,L8,IF($F$5>=640,L7,IF($F$5>=620,L6,0)))))))))) -> 0.0151 | I8: 660-679 | J8: 0.0146 | L8: 0.0552 | M8: 0.0465 | O8: =IF($F$5>=800,S15,IF($F$5>=780,S14,IF($F$5>=760,S13,IF($F$5>=740,S12,IF($F$5>=720,S11,IF($F$5>=700,S10,IF($F$5>=680,S9,IF($F$5>=660,S8,IF($F$5>=640,S7,IF($F$5>=620,S6,0)))))))))) -> 0.0094 | P8: 660-679 | Q8: 0.0077 | S8: 0.0328 | T8: 0.025 | V8: =IF($F$5>=800,Z15,IF($F$5>=780,Z14,IF($F$5>=760,Z13,IF($F$5>=740,Z12,IF($F$5>=720,Z11,IF($F$5>=700,Z10,IF($F$5>=680,Z9,IF($F$5>=660,Z8,IF($F$5>=640,Z7,IF($F$5>=620,Z6,0)))))))))) -> 0.0133 | W8: 660-679 | X8: 0.013 | Z8: 0.053 | AA8: 0.0443 | AC8: =IF($F$5>=800,AG15,IF($F$5>=780,AG14,IF($F$5>=760,AG13,IF($F$5>=740,AG12,IF($F$5>=720,AG11,IF($F$5>=700,AG10,IF($F$5>=680,AG9,IF($F$5>=660,AG8,IF($F$5>=640,AG7,IF($F$5>=620,AG6,0)))))))))) -> 0.0084 | AD8: 660-679 | AE8: 0.0066 | AG8: 0.032 | AH8: 0.0239 | AJ8: Cash To Close Calculations | AP8: Conf Limit | AQ8: 806500
B9: Single PIF | C9: =IF('Payment Summaries'!$E$19="No",F9,F37) -> 0 | E9: Single PIF | F9: =IF($F$4>0.97,0,IF(AND($F$4>0.95,$F$6=1),H8,IF(AND($F$4>0.95,$F$6="Multi"),V8,IF(AND($F$4>0.9,$F$6=1),H21,IF(AND($F$4>0.9,$F$6="Multi"),V21,IF(AND($F$4>0.85,$F$6=1),O8,IF(AND($F$4>0.85,$F$6="Multi"),AC8,IF(AND($F$4>0.8,$F$6=1),O21,IF(AND($F$4>0.8,$F$6="Multi"),AC21,))))))))) -> 0 | H9: =IF($F$5>=800,M15,IF($F$5>=780,M14,IF($F$5>=760,M13,IF($F$5>=740,M12,IF($F$5>=720,M11,IF($F$5>=700,M10,IF($F$5>=680,M9,IF($F$5>=660,M8,IF($F$5>=640,M7,IF($F$5>=620,M6,0)))))))))) -> 0.0158 | I9: 680-699 | J9: 0.01 | L9: 0.0411 | M9: 0.0368 | O9: =IF($F$5>=800,T15,IF($F$5>=780,T14,IF($F$5>=760,T13,IF($F$5>=740,T12,IF($F$5>=720,T11,IF($F$5>=700,T10,IF($F$5>=680,T9,IF($F$5>=660,T8,IF($F$5>=640,T7,IF($F$5>=620,T6,0)))))))))) -> 0.0087 | P9: 680-699 | Q9: 0.0055 | S9: 0.0217 | T9: 0.0199 | V9: =IF($F$5>=800,AA15,IF($F$5>=780,AA14,IF($F$5>=760,AA13,IF($F$5>=740,AA12,IF($F$5>=720,AA11,IF($F$5>=700,AA10,IF($F$5>=680,AA9,IF($F$5>=660,AA8,IF($F$5>=640,AA7,IF($F$5>=620,AA6,0)))))))))) -> 0.014 | W9: 680-699 | X9: 0.0089 | Z9: 0.039 | AA9: 0.0347 | AC9: =IF($F$5>=800,AH15,IF($F$5>=780,AH14,IF($F$5>=760,AH13,IF($F$5>=740,AH12,IF($F$5>=720,AH11,IF($F$5>=700,AH10,IF($F$5>=680,AH9,IF($F$5>=660,AH8,IF($F$5>=640,AH7,IF($F$5>=620,AH6,0)))))))))) -> 0.0077 | AD9: 680-699 | AE9: 0.0045 | AG9: 0.0217 | AH9: 0.0188 | AK9: Per Diem | AM9: 15 Days | AP9: HB Limit | AQ9: 1209750
B10: Single FIN | C10: =IF('Payment Summaries'!$E$19="No",F10,F38) -> 0 | E10: Single Fin | F10: =IF($F$4>0.97,0,IF(AND($F$4>0.95,$F$6=1),H9,IF(AND($F$4>0.95,$F$6="Multi"),V9,IF(AND($F$4>0.9,$F$6=1),H22,IF(AND($F$4>0.9,$F$6="Multi"),V22,IF(AND($F$4>0.85,$F$6=1),O9,IF(AND($F$4>0.85,$F$6="Multi"),AC9,IF(AND($F$4>0.8,$F$6=1),O22,IF(AND($F$4>0.8,$F$6="Multi"),AC22,))))))))) -> 0 | I10: 700-719 | J10: 0.0082 | L10: 0.0331 | M10: 0.0318 | P10: 700-719 | Q10: 0.0043 | S10: 0.0197 | T10: 0.0175 | W10: 700-719 | X10: 0.0073 | Z10: 0.0311 | AA10: 0.0298 | AD10: 700-719 | AE10: 0.0036 | AG10: 0.0187 | AH10: 0.0165 | AJ10: LPMI | AK10: ='Payment Summaries'!K9*'Payment Summaries'!K11/360 -> 0 | AM10: =AK10*15 -> 0
I11: 720-739 | J11: 0.0073 | L11: 0.0277 | M11: 0.0275 | P11: 720-739 | Q11: 0.0036 | R11: 0.00625 | S11: 0.016 | T11: 0.0148 | W11: 720-739 | X11: 0.0065 | Z11: 0.0257 | AA11: 0.0255 | AD11: 720-739 | AE11: 0.003 | AF11: 0.00625 | AG11: 0.0154 | AH11: 0.0138 | AJ11: Single Fin | AK11: ='Payment Summaries'!K26*'Payment Summaries'!K28/360 -> 104.16667 | AM11: =AK11*15 -> 1562.5
E12: Rate | F12: ='Payment Summaries'!$H$11 -> 0.0625 | I12: 740-759 | J12: 0.0059 | L12: 0.0217 | M12: 0.0219 | P12: 740-759 | Q12: 0.0028 | R12: 0.0055 | S12: 0.0134 | T12: 0.0116 | W12: 740-759 | X12: 0.0051 | Z12: 0.0197 | AA12: 0.0199 | AD12: 740-759 | AE12: 0.0024 | AF12: 0.0055 | AG12: 0.0124 | AH12: 0.0106
I13: 760-779 | J13: 0.0045 | K13: 0.00625 | L13: 0.0151 | M13: 0.0158 | P13: 760-779 | Q13: 0.002 | R13: 0.0035 | S13: 0.0094 | T13: 0.0087 | W13: 760-779 | X13: 0.0038 | Y13: 0.0055 | Z13: 0.0133 | AA13: 0.014 | AD13: 760-779 | AE13: 0.0018 | AF13: 0.003 | AG13: 0.0084 | AH13: 0.0077 | AJ13: APR Calcs
I14: 780-799 | J14: 0.0045 | K14: 0.0055 | L14: 0.0133 | M14: 0.0158 | P14: 780-799 | Q14: 0.002 | R14: 0.0025 | S14: 0.0083 | T14: 0.0087 | W14: 780-799 | X14: 0.0038 | Y14: 0.0035 | Z14: 0.0115 | AA14: 0.014 | AD14: 780-799 | AE14: 0.0018 | AF14: 0.002 | AG14: 0.0073 | AH14: 0.0077 | AJ14: Loan Costs | AK14: =SUM('Closing Cost Estimate'!M11:M12,'Closing Cost Estimate'!M16:M17,'Closing Cost Estimate'!M19:M21,'Closing Cost Estimate'!M24:M25,'Closing Cost Estimate'!M29) -> 2442
I15: 800-850 | J15: 0.0043 | K15: 0.0055 | L15: 0.0131 | M15: 0.0158 | P15: 800-850 | Q15: 0.002 | R15: 0.002 | S15: 0.0079 | T15: 0.0087 | W15: 800-850 | X15: 0.0038 | Y15: 0.0035 | Z15: 0.0113 | AA15: 0.014 | AD15: 800-850 | AE15: 0.0016 | AF15: 0.002 | AG15: 0.0069 | AH15: 0.0077 | AJ15: Total PMI | AK15: =SUM('Amortization Schedule'!J:J) -> 0
AJ16: Amount Fin | AK16: ='Payment Summaries'!H9-Calcs!AK14-Calcs!AK15 -> 597558
I17: 5% Down - PMI Premiums - 1 Borrower | P17: 15% Down - PMI Premiums - 1 Borrower | W17: 5% Down - PMI Premiums - Multi Borrower | AD17: 15% Down - PMI Premiums - Multi Borrower | AJ17: APR | AK17: =RATE(360,-'Payment Summaries'!H15,AK16)*12 -> 0.062886544
I18: Fico Range | J18: BPMI | K18: LPMI | L18: Single PIF | M18: Single Fin | P18: Fico Range | Q18: BPMI | R18: LPMI | S18: Single PIF | T18: Single Fin | W18: Fico Range | X18: BPMI | Y18: LPMI | Z18: Single PIF | AA18: Single Fin | AD18: Fico Range | AE18: BPMI | AF18: LPMI | AG18: Single PIF | AH18: Single Fin
H19: =IF($F$5>=800,J28,IF($F$5>=780,J27,IF($F$5>=760,J26,IF($F$5>=740,J25,IF($F$5>=720,J24,IF($F$5>=700,J23,IF($F$5>=680,J22,IF($F$5>=660,J21,IF($F$5>=640,J20,IF($F$5>=620,J19,0)))))))))) -> 0.0031 | I19: 620-639 | J19: 0.0142 | L19: 0.0508 | M19: 0.0444 | O19: =IF($F$5>=800,Q28,IF($F$5>=780,Q27,IF($F$5>=760,Q26,IF($F$5>=740,Q25,IF($F$5>=720,Q24,IF($F$5>=700,Q23,IF($F$5>=680,Q22,IF($F$5>=660,Q21,IF($F$5>=640,Q20,IF($F$5>=620,Q19,0)))))))))) -> 0.0014 | P19: 620-639 | Q19: 0.0044 | R19: 0.00625 | S19: 0.0143 | T19: 0.0127 | V19: =IF($F$5>=800,X28,IF($F$5>=780,X27,IF($F$5>=760,X26,IF($F$5>=740,X25,IF($F$5>=720,X24,IF($F$5>=700,X23,IF($F$5>=680,X22,IF($F$5>=660,X21,IF($F$5>=640,X20,IF($F$5>=620,X19,0)))))))))) -> 0.0024 | W19: 620-639 | X19: 0.0125 | Z19: 0.0483 | AA19: 0.0444 | AC19: =IF($F$5>=800,AE28,IF($F$5>=780,AE27,IF($F$5>=760,AE26,IF($F$5>=740,AE25,IF($F$5>=720,AE24,IF($F$5>=700,AE23,IF($F$5>=680,AE22,IF($F$5>=660,AE21,IF($F$5>=640,AE20,IF($F$5>=620,AE19,0)))))))))) -> 0.0012 | AD19: 620-639 | AE19: 0.0039 | AF19: 0.00625 | AG19: 0.0139 | AH19: 0.0123
H20: =IF($F$5>=800,K28,IF($F$5>=780,K27,IF($F$5>=760,K26,IF($F$5>=740,K25,IF($F$5>=720,K24,IF($F$5>=700,K23,IF($F$5>=680,K22,IF($F$5>=660,K21,IF($F$5>=640,K20,IF($F$5>=620,K19,0)))))))))) -> 0.0055 | I20: 640-659 | J20: 0.0131 | L20: 0.0458 | M20: 0.0391 | O20: =IF($F$5>=800,R28,IF($F$5>=780,R27,IF($F$5>=760,R26,IF($F$5>=740,R25,IF($F$5>=720,R24,IF($F$5>=700,R23,IF($F$5>=680,R22,IF($F$5>=660,R21,IF($F$5>=640,R20,IF($F$5>=620,R19,0)))))))))) -> 0.00125 | P20: 640-659 | Q20: 0.0038 | R20: 0.0055 | S20: 0.0134 | T20: 0.0106 | V20: =IF($F$5>=800,Y28,IF($F$5>=780,Y27,IF($F$5>=760,Y26,IF($F$5>=740,Y25,IF($F$5>=720,Y24,IF($F$5>=700,Y23,IF($F$5>=680,Y22,IF($F$5>=660,Y21,IF($F$5>=640,Y20,IF($F$5>=620,Y19,0)))))))))) -> 0.0035 | W20: 640-659 | X20: 0.0112 | Z20: 0.0439 | AA20: 0.0372 | AC20: =IF($F$5>=800,AF28,IF($F$5>=780,AF27,IF($F$5>=760,AF26,IF($F$5>=740,AF25,IF($F$5>=720,AF24,IF($F$5>=700,AF23,IF($F$5>=680,AF22,IF($F$5>=660,AF21,IF($F$5>=640,AF20,IF($F$5>=620,AF19,0)))))))))) -> 0.00125 | AD20: 640-659 | AE20: 0.0033 | AF20: 0.00625 | AG20: 0.013 | AH20: 0.0102
H21: =IF($F$5>=800,L28,IF($F$5>=780,L27,IF($F$5>=760,L26,IF($F$5>=740,L25,IF($F$5>=720,L24,IF($F$5>=700,L23,IF($F$5>=680,L22,IF($F$5>=660,L21,IF($F$5>=640,L20,IF($F$5>=620,L19,0)))))))))) -> 0.0124 | I21: 660-679 | J21: 0.0116 | L21: 0.0421 | M21: 0.0369 | O21: =IF($F$5>=800,S28,IF($F$5>=780,S27,IF($F$5>=760,S26,IF($F$5>=740,S25,IF($F$5>=720,S24,IF($F$5>=700,S23,IF($F$5>=680,S22,IF($F$5>=660,S21,IF($F$5>=640,S20,IF($F$5>=620,S19,0)))))))))) -> 0.0047 | P21: 660-679 | Q21: 0.0031 | R21: 0.0055 | S21: 0.0121 | T21: 0.01 | V21: =IF($F$5>=800,Z28,IF($F$5>=780,Z27,IF($F$5>=760,Z26,IF($F$5>=740,Z25,IF($F$5>=720,Z24,IF($F$5>=700,Z23,IF($F$5>=680,Z22,IF($F$5>=660,Z21,IF($F$5>=640,Z20,IF($F$5>=620,Z19,0)))))))))) -> 0.011 | W21: 660-679 | X21: 0.0102 | Z21: 0.0404 | AA21: 0.0352 | AC21: =IF($F$5>=800,AG28,IF($F$5>=780,AG27,IF($F$5>=760,AG26,IF($F$5>=740,AG25,IF($F$5>=720,AG24,IF($F$5>=700,AG23,IF($F$5>=680,AG22,IF($F$5>=660,AG21,IF($F$5>=640,AG20,IF($F$5>=620,AG19,0)))))))))) -> 0.0044 | AD21: 660-679 | AE21: 0.0025 | AF21: 0.0055 | AG21: 0.0117 | AH21: 0.0096
H22: =IF($F$5>=800,M28,IF($F$5>=780,M27,IF($F$5>=760,M26,IF($F$5>=740,M25,IF($F$5>=720,M24,IF($F$5>=700,M23,IF($F$5>=680,M22,IF($F$5>=660,M21,IF($F$5>=640,M20,IF($F$5>=620,M19,0)))))))))) -> 0.0122 | I22: 680-699 | J22: 0.0074 | L22: 0.0318 | M22: 0.0292 | O22: =IF($F$5>=800,T28,IF($F$5>=780,T27,IF($F$5>=760,T26,IF($F$5>=740,T25,IF($F$5>=720,T24,IF($F$5>=700,T23,IF($F$5>=680,T22,IF($F$5>=660,T21,IF($F$5>=640,T20,IF($F$5>=620,T19,0)))))))))) -> 0.0047 | P22: 680-699 | Q22: 0.0022 | R22: 0.0035 | S22: 0.009 | T22: 0.0085 | V22: =IF($F$5>=800,AA28,IF($F$5>=780,AA27,IF($F$5>=760,AA26,IF($F$5>=740,AA25,IF($F$5>=720,AA24,IF($F$5>=700,AA23,IF($F$5>=680,AA22,IF($F$5>=660,AA21,IF($F$5>=640,AA20,IF($F$5>=620,AA19,0)))))))))) -> 0.0108 | W22: 680-699 | X22: 0.0064 | Z22: 0.0302 | AA22: 0.0276 | AC22: =IF($F$5>=800,AH28,IF($F$5>=780,AH27,IF($F$5>=760,AH26,IF($F$5>=740,AH25,IF($F$5>=720,AH24,IF($F$5>=700,AH23,IF($F$5>=680,AH22,IF($F$5>=660,AH21,IF($F$5>=640,AH20,IF($F$5>=620,AH19,0)))))))))) -> 0.0044 | AD22: 680-699 | AE22: 0.0018 | AF22: 0.0025 | AG22: 0.0086 | AH22: 0.0081
I23: 700-719 | J23: 0.0059 | L23: 0.0257 | M23: 0.0252 | P23: 700-719 | Q23: 0.002 | R23: 0.002 | S23: 0.0077 | T23: 0.0071 | W23: 700-719 | X23: 0.0052 | Z23: 0.0257 | AA23: 0.0236 | AD23: 700-719 | AE23: 0.0016 | AF23: 0.002 | AG23: 0.0074 | AH23: 0.0068
I24: 720-739 | J24: 0.005 | L24: 0.0217 | M24: 0.0216 | P24: 720-739 | Q24: 0.0018 | R24: 0.002 | S24: 0.0067 | T24: 0.0064 | W24: 720-739 | X24: 0.0043 | Z24: 0.0203 | AA24: 0.0202 | AD24: 720-739 | AE24: 0.0016 | AF24: 0.002 | AG24: 0.0064 | AH24: 0.0061
I25: 740-759 | J25: 0.0042 | K25: 0.00875 | L25: 0.0174 | M25: 0.0173 | P25: 740-759 | Q25: 0.0016 | R25: 0.002 | S25: 0.0057 | T25: 0.0054 | W25: 740-759 | X25: 0.0035 | Y25: 0.00625 | Z25: 0.016 | AA25: 0.0159 | AD25: 740-759 | AE25: 0.0012 | AF25: 0.00125 | AG25: 0.0054 | AH25: 0.0051
I26: 760-779 | J26: 0.0031 | K26: 0.0055 | L26: 0.0124 | M26: 0.0122 | P26: 760-779 | Q26: 0.0014 | R26: 0.00125 | S26: 0.0047 | T26: 0.0047 | W26: 760-779 | X26: 0.0024 | Y26: 0.0035 | Z26: 0.011 | AA26: 0.0108 | AD26: 760-779 | AE26: 0.0012 | AF26: 0.00125 | AG26: 0.0044 | AH26: 0.0044
I27: 780-799 | J27: 0.0031 | K27: 0.0035 | L27: 0.0103 | M27: 0.0122 | P27: 780-799 | Q27: 0.0014 | R27: 0.00125 | S27: 0.0047 | T27: 0.0047 | W27: 780-799 | X27: 0.0024 | Y27: 0.003 | Z27: 0.0089 | AA27: 0.0108 | AD27: 780-799 | AE27: 0.0012 | AF27: 0.00125 | AG27: 0.0044 | AH27: 0.0044
I28: 800-850 | J28: 0.0029 | K28: 0.0035 | L28: 0.0096 | M28: 0.0122 | P28: 800-850 | Q28: 0.0014 | R28: 0.00125 | S28: 0.0047 | T28: 0.0047 | W28: 800-850 | X28: 0.0024 | Y28: 0.003 | Z28: 0.0082 | AA28: 0.0108 | AD28: 800-850 | AE28: 0.0012 | AF28: 0.00125 | AG28: 0.0044 | AH28: 0.0044
I30: 30 Yr Term - Black Box PMI Rates - HomePossible/HomeReady
E32: LTV | F32: =1-'Payment Summaries'!$E$15 -> 0.8 | I32: Home Poss - 3% Down - PMI Premiums - 1 Borrower | P32: Home Poss - 10% Down - PMI Premiums - 1 Borrower | W32: Home Poss - 3% Down - PMI Premiums - Multi Borrower | AD32: Home Poss - 10% Down - PMI Premiums - Multi Borrower
E33: Fico Score | F33: ='Payment Summaries'!$E$16 -> 771 | I33: Fico Range | J33: BPMI | K33: LPMI | L33: Single PIF | M33: Single Fin | P33: Fico Range | Q33: BPMI | R33: LPMI | S33: Single PIF | T33: Single Fin | W33: Fico Range | X33: BPMI | Y33: LPMI | Z33: Single PIF | AA33: Single Fin | AD33: Fico Range | AE33: BPMI | AF33: LPMI | AG33: Single PIF | AH33: Single Fin
E34: # of Borr | F34: ='Payment Summaries'!$E$17 -> Multi | H34: =IF($F$33>=800,J43,IF($F$33>=780,J42,IF($F$33>=760,J41,IF($F$33>=740,J40,IF($F$33>=720,J39,IF($F$33>=700,J38,IF($F$33>=680,J37,IF($F$33>=660,J36,IF($F$33>=640,J35,IF($F$33>=620,J34,0)))))))))) -> 0.0041 | I34: 620-639 | J34: 0.015 | L34: 0.0498 | M34: 0.0412 | O34: =IF($F$33>=800,Q43,IF($F$33>=780,Q42,IF($F$33>=760,Q41,IF($F$33>=740,Q40,IF($F$33>=720,Q39,IF($F$33>=700,Q38,IF($F$33>=680,Q37,IF($F$33>=660,Q36,IF($F$33>=640,Q35,IF($F$33>=620,Q34,0)))))))))) -> 0.002 | P34: 620-639 | Q34: 0.0085 | S34: 0.0384 | T34: 0.0281 | V34: =IF($F$33>=800,X43,IF($F$33>=780,X42,IF($F$33>=760,X41,IF($F$33>=740,X40,IF($F$33>=720,X39,IF($F$33>=700,X38,IF($F$33>=680,X37,IF($F$33>=660,X36,IF($F$33>=640,X35,IF($F$33>=620,X34,0)))))))))) -> 0.0027 | W34: 620-639 | X34: 0.0132 | Z34: 0.0471 | AA34: 0.0412 | AC34: =IF($F$33>=800,AE43,IF($F$33>=780,AE42,IF($F$33>=760,AE41,IF($F$33>=740,AE40,IF($F$33>=720,AE39,IF($F$33>=700,AE38,IF($F$33>=680,AE37,IF($F$33>=660,AE36,IF($F$33>=640,AE35,IF($F$33>=620,AE34,0)))))))))) -> 0.0018 | AD34: 620-639 | AE34: 0.007 | AG34: 0.0369 | AH34: 0.0281
E35: BPMI | F35: =IF($F$32>0.97,0,IF(AND($F$32>0.95,$F$34=1),H34,IF(AND($F$32>0.95,$F$34="Multi"),V34,IF(AND($F$32>0.9,$F$34=1),H47,IF(AND($F$32>0.9,$F$34="Multi"),V47,IF(AND($F$32>0.85,$F$34=1),O34,IF(AND($F$32>0.85,$F$34="Multi"),AC34,IF(AND($F$32>0.8,$F$34=1),O47,IF(AND($F$32>0.8,$F$34="Multi"),AC47,))))))))) -> 0 | H35: =IF($F$33>=800,K43,IF($F$33>=780,K42,IF($F$33>=760,K41,IF($F$33>=740,K40,IF($F$33>=720,K39,IF($F$33>=700,K38,IF($F$33>=680,K37,IF($F$33>=660,K36,IF($F$33>=640,K35,IF($F$33>=620,K34,0)))))))))) -> 0.0055 | I35: 640-659 | J35: 0.0131 | L35: 0.0451 | M35: 0.041 | O35: =IF($F$33>=800,R43,IF($F$33>=780,R42,IF($F$33>=760,R41,IF($F$33>=740,R40,IF($F$33>=720,R39,IF($F$33>=700,R38,IF($F$33>=680,R37,IF($F$33>=660,R36,IF($F$33>=640,R35,IF($F$33>=620,R34,0)))))))))) -> 0.0035 | P35: 640-659 | Q35: 0.0085 | S35: 0.0351 | T35: 0.0265 | V35: =IF($F$33>=800,Y43,IF($F$33>=780,Y42,IF($F$33>=760,Y41,IF($F$33>=740,Y40,IF($F$33>=720,Y39,IF($F$33>=700,Y38,IF($F$33>=680,Y37,IF($F$33>=660,Y36,IF($F$33>=640,Y35,IF($F$33>=620,Y34,0)))))))))) -> 0.0035 | W35: 640-659 | X35: 0.0113 | Z35: 0.0428 | AA35: 0.0387 | AC35: =IF($F$33>=800,AF43,IF($F$33>=780,AF42,IF($F$33>=760,AF41,IF($F$33>=740,AF40,IF($F$33>=720,AF39,IF($F$33>=700,AF38,IF($F$33>=680,AF37,IF($F$33>=660,AF36,IF($F$33>=640,AF35,IF($F$33>=620,AF34,0)))))))))) -> 0.003 | AD35: 640-659 | AE35: 0.0071 | AG35: 0.0339 | AH35: 0.0253
E36: LPMI | F36: =IF($F$32>0.97,0,IF(AND($F$32>0.95,$F$34=1),F40+H35,IF(AND($F$32>0.95,$F$34="Multi"),F40+V35,IF(AND($F$32>0.9,$F$34=1),F40+H48,IF(AND($F$32>0.9,$F$34="Multi"),F40+V48,IF(AND($F$32>0.85,$F$34=1),F40+O35,IF(AND($F$32>0.85,$F$34="Multi"),F40+AC35,IF(AND($F$32>0.8,$F$34=1),F40+O48,IF(AND($F$32>0.8,$F$34="Multi"),F40+AC48,))))))))) -> 0 | H36: =IF($F$33>=800,L43,IF($F$33>=780,L42,IF($F$33>=760,L41,IF($F$33>=740,L40,IF($F$33>=720,L39,IF($F$33>=700,L38,IF($F$33>=680,L37,IF($F$33>=660,L36,IF($F$33>=640,L35,IF($F$33>=620,L34,0)))))))))) -> 0.0117 | I36: 660-679 | J36: 0.0117 | L36: 0.0411 | M36: 0.0386 | O36: =IF($F$33>=800,S43,IF($F$33>=780,S42,IF($F$33>=760,S41,IF($F$33>=740,S40,IF($F$33>=720,S39,IF($F$33>=700,S38,IF($F$33>=680,S37,IF($F$33>=660,S36,IF($F$33>=640,S35,IF($F$33>=620,S34,0)))))))))) -> 0.0094 | P36: 660-679 | Q36: 0.0077 | S36: 0.0328 | T36: 0.025 | V36: =IF($F$33>=800,Z43,IF($F$33>=780,Z42,IF($F$33>=760,Z41,IF($F$33>=740,Z40,IF($F$33>=720,Z39,IF($F$33>=700,Z38,IF($F$33>=680,Z37,IF($F$33>=660,Z36,IF($F$33>=640,Z35,IF($F$33>=620,Z34,0)))))))))) -> 0.0099 | W36: 660-679 | X36: 0.0101 | Z36: 0.0389 | AA36: 0.0364 | AC36: =IF($F$33>=800,AG43,IF($F$33>=780,AG42,IF($F$33>=760,AG41,IF($F$33>=740,AG40,IF($F$33>=720,AG39,IF($F$33>=700,AG38,IF($F$33>=680,AG37,IF($F$33>=660,AG36,IF($F$33>=640,AG35,IF($F$33>=620,AG34,0)))))))))) -> 0.0084 | AD36: 660-679 | AE36: 0.0066 | AG36: 0.032 | AH36: 0.0239
E37: Single PIF | F37: =IF($F$32>0.97,0,IF(AND($F$32>0.95,$F$34=1),H36,IF(AND($F$32>0.95,$F$34="Multi"),V36,IF(AND($F$32>0.9,$F$34=1),H49,IF(AND($F$32>0.9,$F$34="Multi"),V49,IF(AND($F$32>0.85,$F$34=1),O36,IF(AND($F$32>0.85,$F$34="Multi"),AC36,IF(AND($F$32>0.8,$F$34=1),O49,IF(AND($F$32>0.8,$F$34="Multi"),AC49,))))))))) -> 0 | H37: =IF($F$33>=800,M43,IF($F$33>=780,M42,IF($F$33>=760,M41,IF($F$33>=740,M40,IF($F$33>=720,M39,IF($F$33>=700,M38,IF($F$33>=680,M37,IF($F$33>=660,M36,IF($F$33>=640,M35,IF($F$33>=620,M34,0)))))))))) -> 0.0136 | I37: 680-699 | J37: 0.0082 | L37: 0.0307 | M37: 0.0306 | O37: =IF($F$33>=800,T43,IF($F$33>=780,T42,IF($F$33>=760,T41,IF($F$33>=740,T40,IF($F$33>=720,T39,IF($F$33>=700,T38,IF($F$33>=680,T37,IF($F$33>=660,T36,IF($F$33>=640,T35,IF($F$33>=620,T34,0)))))))))) -> 0.0087 | P37: 680-699 | Q37: 0.0055 | S37: 0.0217 | T37: 0.0199 | V37: =IF($F$33>=800,AA43,IF($F$33>=780,AA42,IF($F$33>=760,AA41,IF($F$33>=740,AA40,IF($F$33>=720,AA39,IF($F$33>=700,AA38,IF($F$33>=680,AA37,IF($F$33>=660,AA36,IF($F$33>=640,AA35,IF($F$33>=620,AA34,0)))))))))) -> 0.0118 | W37: 680-699 | X37: 0.0071 | Z37: 0.0286 | AA37: 0.0285 | AC37: =IF($F$33>=800,AH43,IF($F$33>=780,AH42,IF($F$33>=760,AH41,IF($F$33>=740,AH40,IF($F$33>=720,AH39,IF($F$33>=700,AH38,IF($F$33>=680,AH37,IF($F$33>=660,AH36,IF($F$33>=640,AH35,IF($F$33>=620,AH34,0)))))))))) -> 0.0077 | AD37: 680-699 | AE37: 0.0045 | AG37: 0.0217 | AH37: 0.0188
E38: Single Fin | F38: =IF($F$32>0.97,0,IF(AND($F$32>0.95,$F$34=1),H37,IF(AND($F$32>0.95,$F$34="Multi"),V37,IF(AND($F$32>0.9,$F$34=1),H50,IF(AND($F$32>0.9,$F$34="Multi"),V50,IF(AND($F$32>0.85,$F$34=1),O37,IF(AND($F$32>0.85,$F$34="Multi"),AC37,IF(AND($F$32>0.8,$F$34=1),O50,IF(AND($F$32>0.8,$F$34="Multi"),AC50,))))))))) -> 0 | I38: 700-719 | J38: 0.0071 | L38: 0.0247 | M38: 0.0265 | P38: 700-719 | Q38: 0.0043 | S38: 0.0197 | T38: 0.0175 | W38: 700-719 | X38: 0.0062 | Z38: 0.0227 | AA38: 0.0245 | AD38: 700-719 | AE38: 0.0036 | AG38: 0.0187 | AH38: 0.0165
I39: 720-739 | J39: 0.0061 | L39: 0.021 | M39: 0.0231 | P39: 720-739 | Q39: 0.0036 | R39: 0.00625 | S39: 0.016 | T39: 0.0148 | W39: 720-739 | X39: 0.0051 | Z39: 0.019 | AA39: 0.0211 | AD39: 720-739 | AE39: 0.003 | AF39: 0.00625 | AG39: 0.0154 | AH39: 0.0138
E40: Rate | F40: ='Payment Summaries'!$H$11 -> 0.0625 | I40: 740-759 | J40: 0.0052 | K40: 0.00875 | L40: 0.0167 | M40: 0.0188 | P40: 740-759 | Q40: 0.0028 | R40: 0.0055 | S40: 0.0134 | T40: 0.0116 | W40: 740-759 | X40: 0.0043 | Y40: 0.00625 | Z40: 0.0147 | AA40: 0.0168 | AD40: 740-759 | AE40: 0.0024 | AF40: 0.0055 | AG40: 0.0124 | AH40: 0.0106
I41: 760-779 | J41: 0.0041 | K41: 0.0055 | L41: 0.0117 | M41: 0.0136 | P41: 760-779 | Q41: 0.002 | R41: 0.0035 | S41: 0.0094 | T41: 0.0087 | W41: 760-779 | X41: 0.0027 | Y41: 0.0035 | Z41: 0.0099 | AA41: 0.0118 | AD41: 760-779 | AE41: 0.0018 | AF41: 0.003 | AG41: 0.0084 | AH41: 0.0077
I42: 780-799 | J42: 0.0041 | K42: 0.0055 | L42: 0.0111 | M42: 0.0136 | P42: 780-799 | Q42: 0.002 | R42: 0.0025 | S42: 0.0083 | T42: 0.0087 | W42: 780-799 | X42: 0.0027 | Y42: 0.0035 | Z42: 0.0093 | AA42: 0.0118 | AD42: 780-799 | AE42: 0.0018 | AF42: 0.002 | AG42: 0.0073 | AH42: 0.0077
I43: 800-850 | J43: 0.0039 | K43: 0.0035 | L43: 0.0108 | M43: 0.0136 | P43: 800-850 | Q43: 0.002 | R43: 0.002 | S43: 0.0079 | T43: 0.0087 | W43: 800-850 | X43: 0.0027 | Y43: 0.003 | Z43: 0.009 | AA43: 0.0118 | AD43: 800-850 | AE43: 0.0016 | AF43: 0.002 | AG43: 0.0069 | AH43: 0.0077
I45: Home Poss - 5% Down - PMI Premiums - 1 Borrower | P45: Home Poss - 15% Down - PMI Premiums - 1 Borrower | W45: Home Poss - 5% Down - PMI Premiums - Multi Borrower | AD45: Home Poss - 15% Down - PMI Premiums - Multi Borrower
I46: Fico Range | J46: BPMI | K46: LPMI | L46: Single PIF | M46: Single Fin | P46: Fico Range | Q46: BPMI | R46: LPMI | S46: Single PIF | T46: Single Fin | W46: Fico Range | X46: BPMI | Y46: LPMI | Z46: Single PIF | AA46: Single Fin | AD46: Fico Range | AE46: BPMI | AF46: LPMI | AG46: Single PIF | AH46: Single Fin
H47: =IF($F$33>=800,J56,IF($F$33>=780,J55,IF($F$33>=760,J54,IF($F$33>=740,J53,IF($F$33>=720,J52,IF($F$33>=700,J51,IF($F$33>=680,J50,IF($F$33>=660,J49,IF($F$33>=640,J48,IF($F$33>=620,J47,0)))))))))) -> 0.0031 | I47: 620-639 | J47: 0.0125 | L47: 0.0434 | M47: 0.04 | O47: =IF($F$33>=800,Q56,IF($F$33>=780,Q55,IF($F$33>=760,Q54,IF($F$33>=740,Q53,IF($F$33>=720,Q52,IF($F$33>=700,Q51,IF($F$33>=680,Q50,IF($F$33>=660,Q49,IF($F$33>=640,Q48,IF($F$33>=620,Q47,0)))))))))) -> 0.0014 | P47: 620-639 | Q47: 0.0044 | R47: 0.00625 | S47: 0.0143 | T47: 0.0127 | V47: =IF($F$33>=800,X56,IF($F$33>=780,X55,IF($F$33>=760,X54,IF($F$33>=740,X53,IF($F$33>=720,X52,IF($F$33>=700,X51,IF($F$33>=680,X50,IF($F$33>=660,X49,IF($F$33>=640,X48,IF($F$33>=620,X47,0)))))))))) -> 0.0022 | W47: 620-639 | X47: 0.0109 | Z47: 0.0409 | AA47: 0.04 | AC47: =IF($F$33>=800,AE56,IF($F$33>=780,AE55,IF($F$33>=760,AE54,IF($F$33>=740,AE53,IF($F$33>=720,AE52,IF($F$33>=700,AE51,IF($F$33>=680,AE50,IF($F$33>=660,AE49,IF($F$33>=640,AE48,IF($F$33>=620,AE47,0)))))))))) -> 0.0012 | AD47: 620-639 | AE47: 0.0039 | AF47: 0.00625 | AG47: 0.0139 | AH47: 0.0123
H48: =IF($F$33>=800,K56,IF($F$33>=780,K55,IF($F$33>=760,K54,IF($F$33>=740,K53,IF($F$33>=720,K52,IF($F$33>=700,K51,IF($F$33>=680,K50,IF($F$33>=660,K49,IF($F$33>=640,K48,IF($F$33>=620,K47,0)))))))))) -> 0.0035 | I48: 640-659 | J48: 0.0114 | L48: 0.0394 | M48: 0.0374 | O48: =IF($F$33>=800,R56,IF($F$33>=780,R55,IF($F$33>=760,R54,IF($F$33>=740,R53,IF($F$33>=720,R52,IF($F$33>=700,R51,IF($F$33>=680,R50,IF($F$33>=660,R49,IF($F$33>=640,R48,IF($F$33>=620,R47,0)))))))))) -> 0.00125 | P48: 640-659 | Q48: 0.0038 | R48: 0.0055 | S48: 0.0134 | T48: 0.0106 | V48: =IF($F$33>=800,Y56,IF($F$33>=780,Y55,IF($F$33>=760,Y54,IF($F$33>=740,Y53,IF($F$33>=720,Y52,IF($F$33>=700,Y51,IF($F$33>=680,Y50,IF($F$33>=660,Y49,IF($F$33>=640,Y48,IF($F$33>=620,Y47,0)))))))))) -> 0.0035 | W48: 640-659 | X48: 0.0095 | Z48: 0.0375 | AA48: 0.0355 | AC48: =IF($F$33>=800,AF56,IF($F$33>=780,AF55,IF($F$33>=760,AF54,IF($F$33>=740,AF53,IF($F$33>=720,AF52,IF($F$33>=700,AF51,IF($F$33>=680,AF50,IF($F$33>=660,AF49,IF($F$33>=640,AF48,IF($F$33>=620,AF47,0)))))))))) -> 0.00125 | AD48: 640-659 | AE48: 0.0033 | AF48: 0.00625 | AG48: 0.013 | AH48: 0.0102
H49: =IF($F$33>=800,L56,IF($F$33>=780,L55,IF($F$33>=760,L54,IF($F$33>=740,L53,IF($F$33>=720,L52,IF($F$33>=700,L51,IF($F$33>=680,L50,IF($F$33>=660,L49,IF($F$33>=640,L48,IF($F$33>=620,L47,0)))))))))) -> 0.0107 | I49: 660-679 | J49: 0.0099 | L49: 0.0361 | M49: 0.0352 | O49: =IF($F$33>=800,S56,IF($F$33>=780,S55,IF($F$33>=760,S54,IF($F$33>=740,S53,IF($F$33>=720,S52,IF($F$33>=700,S51,IF($F$33>=680,S50,IF($F$33>=660,S49,IF($F$33>=640,S48,IF($F$33>=620,S47,0)))))))))) -> 0.0047 | P49: 660-679 | Q49: 0.0031 | R49: 0.0055 | S49: 0.0121 | T49: 0.01 | V49: =IF($F$33>=800,Z56,IF($F$33>=780,Z55,IF($F$33>=760,Z54,IF($F$33>=740,Z53,IF($F$33>=720,Z52,IF($F$33>=700,Z51,IF($F$33>=680,Z50,IF($F$33>=660,Z49,IF($F$33>=640,Z48,IF($F$33>=620,Z47,0)))))))))) -> 0.0093 | W49: 660-679 | X49: 0.0085 | Z49: 0.0344 | AA49: 0.0335 | AC49: =IF($F$33>=800,AG56,IF($F$33>=780,AG55,IF($F$33>=760,AG54,IF($F$33>=740,AG53,IF($F$33>=720,AG52,IF($F$33>=700,AG51,IF($F$33>=680,AG50,IF($F$33>=660,AG49,IF($F$33>=640,AG48,IF($F$33>=620,AG47,0)))))))))) -> 0.0044 | AD49: 660-679 | AE49: 0.0025 | AF49: 0.0055 | AG49: 0.0117 | AH49: 0.0096
H50: =IF($F$33>=800,M56,IF($F$33>=780,M55,IF($F$33>=760,M54,IF($F$33>=740,M53,IF($F$33>=720,M52,IF($F$33>=700,M51,IF($F$33>=680,M50,IF($F$33>=660,M49,IF($F$33>=640,M48,IF($F$33>=620,M47,0)))))))))) -> 0.012 | I50: 680-699 | J50: 0.0073 | L50: 0.0274 | M50: 0.0279 | O50: =IF($F$33>=800,T56,IF($F$33>=780,T55,IF($F$33>=760,T54,IF($F$33>=740,T53,IF($F$33>=720,T52,IF($F$33>=700,T51,IF($F$33>=680,T50,IF($F$33>=660,T49,IF($F$33>=640,T48,IF($F$33>=620,T47,0)))))))))) -> 0.0047 | P50: 680-699 | Q50: 0.0022 | R50: 0.0035 | S50: 0.009 | T50: 0.0085 | V50: =IF($F$33>=800,AA56,IF($F$33>=780,AA55,IF($F$33>=760,AA54,IF($F$33>=740,AA53,IF($F$33>=720,AA52,IF($F$33>=700,AA51,IF($F$33>=680,AA50,IF($F$33>=660,AA49,IF($F$33>=640,AA48,IF($F$33>=620,AA47,0)))))))))) -> 0.0106 | W50: 680-699 | X50: 0.0061 | Z50: 0.0258 | AA50: 0.0263 | AC50: =IF($F$33>=800,AH56,IF($F$33>=780,AH55,IF($F$33>=760,AH54,IF($F$33>=740,AH53,IF($F$33>=720,AH52,IF($F$33>=700,AH51,IF($F$33>=680,AH50,IF($F$33>=660,AH49,IF($F$33>=640,AH48,IF($F$33>=620,AH47,0)))))))))) -> 0.0044 | AD50: 680-699 | AE50: 0.0018 | AF50: 0.0025 | AG50: 0.0086 | AH50: 0.0081
I51: 700-719 | J51: 0.0058 | L51: 0.0221 | M51: 0.0241 | P51: 700-719 | Q51: 0.002 | R51: 0.002 | S51: 0.0077 | T51: 0.0071 | W51: 700-719 | X51: 0.005 | Z51: 0.0205 | AA51: 0.0225 | AD51: 700-719 | AE51: 0.0016 | AF51: 0.002 | AG51: 0.0074 | AH51: 0.0068
I52: 720-739 | J52: 0.005 | L52: 0.0187 | M52: 0.0211 | P52: 720-739 | Q52: 0.0018 | R52: 0.002 | S52: 0.0067 | T52: 0.0064 | W52: 720-739 | X52: 0.0042 | Y52: 0.00875 | Z52: 0.0173 | AA52: 0.0197 | AD52: 720-739 | AE52: 0.0016 | AF52: 0.002 | AG52: 0.0064 | AH52: 0.0061
I53: 740-759 | J53: 0.004 | K53: 0.00625 | L53: 0.0151 | M53: 0.0159 | P53: 740-759 | Q53: 0.0016 | R53: 0.002 | S53: 0.0057 | T53: 0.0054 | W53: 740-759 | X53: 0.0034 | Y53: 0.00625 | Z53: 0.0137 | AA53: 0.0145 | AD53: 740-759 | AE53: 0.0012 | AF53: 0.00125 | AG53: 0.0054 | AH53: 0.0051
I54: 760-779 | J54: 0.0031 | K54: 0.0035 | L54: 0.0107 | M54: 0.012 | P54: 760-779 | Q54: 0.0014 | R54: 0.00125 | S54: 0.0047 | T54: 0.0047 | W54: 760-779 | X54: 0.0022 | Y54: 0.0035 | Z54: 0.0093 | AA54: 0.0106 | AD54: 760-779 | AE54: 0.0012 | AF54: 0.00125 | AG54: 0.0044 | AH54: 0.0044
I55: 780-799 | J55: 0.0031 | K55: 0.0025 | L55: 0.009 | M55: 0.012 | P55: 780-799 | Q55: 0.0014 | R55: 0.00125 | S55: 0.0047 | T55: 0.0047 | W55: 780-799 | X55: 0.0022 | Y55: 0.002 | Z55: 0.0076 | AA55: 0.0106 | AD55: 780-799 | AE55: 0.0012 | AF55: 0.00125 | AG55: 0.0044 | AH55: 0.0044
I56: 800-850 | J56: 0.0029 | K56: 0.0025 | L56: 0.0084 | M56: 0.012 | P56: 800-850 | Q56: 0.0014 | R56: 0.00125 | S56: 0.0047 | T56: 0.0047 | W56: 800-850 | X56: 0.0022 | Y56: 0.002 | Z56: 0.007 | AA56: 0.0106 | AD56: 800-850 | AE56: 0.0012 | AF56: 0.00125 | AG56: 0.0044 | AH56: 0.0044
